crypto_pnl/__init__.py
crypto_pnl/__main__.py
crypto_pnl/asset.py
crypto_pnl/console_render.py
crypto_pnl/console_report.py
crypto_pnl/console_walk.py
crypto_pnl/core.py
crypto_pnl/csv_export.py
crypto_pnl/exchange_rate_calculator.py
crypto_pnl/journal.py
crypto_pnl/last_prices.py
crypto_pnl/ledger.py
crypto_pnl/market_data.py
crypto_pnl/position.py
crypto_pnl/summary.py
crypto_pnl/tracker.py
crypto_pnl/trade.py
crypto_pnl/transaction.py
crypto_pnl/wallet.py
crypto_pnl-0.5.2.dist-info/LICENSE
crypto_pnl-0.5.2.dist-info/METADATA
crypto_pnl-0.5.2.dist-info/WHEEL
crypto_pnl-0.5.2.dist-info/entry_points.txt
crypto_pnl-0.5.2.dist-info/top_level.txt
crypto_pnl-0.5.2.dist-info/RECORD
