Metadata-Version: 2.1
Name: crypto-pnl
Version: 0.5.2
Summary: Crypto Trading Realized PnL Calculation (in EUR)
Home-page: https://github.com/sadhbh-c0d3/crypto-pnl
Author: Sonia Kolasinska
Author-email: sonia.kolasinska.pro@gmail.com
Maintainer: Sonia Kolasinska
Maintainer-email: sonia.kolasinska.pro@gmail.com
License: MIT
Platform: UNKNOWN
Classifier: Development Status :: 4 - Beta
Classifier: Intended Audience :: End Users/Desktop
Classifier: License :: OSI Approved :: MIT License
Classifier: Topic :: Office/Business :: Financial
Classifier: Topic :: Office/Business :: Financial :: Accounting
Classifier: Topic :: Office/Business :: Financial :: Spreadsheet
License-File: LICENSE
Requires-Dist: pytz
